mlpl/__init__.py
mlpl/encodingpred.py
mlpl/fe.py
mlpl/models.py
mlpl/prep.py
mlpl/search.py
mlpl/selection.py
mlpl/utils.py
mlpl/vis.py
mlpl/count_encoding_model/countencoding_model_ieee
mlpl/count_encoding_model/countencoding_model_ieee_scaler
mlpl/pipetools/__init__.py
mlpl/pipetools/dt.py
mlpl/pipetools/pdefaults.py
mlpl/pipetools/pipe.py
mlpl/pipetools/pmodels.py
mlpl/pipetools/putils.py
mlpl/pipetools/steps.py
mlpl-0.1.1.data/data/countencoding_model_ieee
mlpl-0.1.1.data/data/countencoding_model_ieee_scaler
mlpl-0.1.1.data/scripts/dt.py
mlpl-0.1.1.data/scripts/encodingpred.py
mlpl-0.1.1.data/scripts/fe.py
mlpl-0.1.1.data/scripts/models.py
mlpl-0.1.1.data/scripts/pdefaults.py
mlpl-0.1.1.data/scripts/pipe.py
mlpl-0.1.1.data/scripts/pmodels.py
mlpl-0.1.1.data/scripts/prep.py
mlpl-0.1.1.data/scripts/putils.py
mlpl-0.1.1.data/scripts/search.py
mlpl-0.1.1.data/scripts/selection.py
mlpl-0.1.1.data/scripts/steps.py
mlpl-0.1.1.data/scripts/utils.py
mlpl-0.1.1.data/scripts/vis.py
mlpl-0.1.1.dist-info/LICENSE
mlpl-0.1.1.dist-info/METADATA
mlpl-0.1.1.dist-info/WHEEL
mlpl-0.1.1.dist-info/top_level.txt
mlpl-0.1.1.dist-info/RECORD
