Metadata-Version: 2.1
Name: mlpl
Version: 0.1.1
Summary: A data science pipeline tool to speed up data science life cycle.
Home-page: https://github.com/ozanzgur/mlpl
Author: Ozan Özgür
Author-email: ozan.zgur@gmail.com
License: UNKNOWN
Platform: UNKNOWN
Classifier: Development Status :: 3 - Alpha
Classifier: Programming Language :: Python :: 3
Classifier: License :: OSI Approved :: GNU General Public License v3 (GPLv3)
Classifier: Operating System :: OS Independent
Classifier: Topic :: Software Development :: Libraries :: Python Modules
Requires-Dist: dill (>=0.3.1.1)
Requires-Dist: hyperopt (>=0.2.2)
Requires-Dist: ipython (>=7.7.0)
Requires-Dist: jupyter (>=1.0.0)
Requires-Dist: pandas (>=0.25.1)
Requires-Dist: scikit-learn (>=0.21.2)
Requires-Dist: scipy (>=1.3.0)
Requires-Dist: tqdm (>=4.36.1)
Requires-Dist: lightgbm (>=2.2.3)
Requires-Dist: json5 (>=0.8.5)
